ms_auth_router/__init__.py
ms_auth_router/apps.py
ms_auth_router/routers.py
dj_ms_auth_router-1.5.1.dist-info/LICENSE
dj_ms_auth_router-1.5.1.dist-info/METADATA
dj_ms_auth_router-1.5.1.dist-info/WHEEL
dj_ms_auth_router-1.5.1.dist-info/top_level.txt
dj_ms_auth_router-1.5.1.dist-info/RECORD
